neopixel.py
adafruit_circuitpython_neopixel-6.3.9.dist-info/LICENSE
adafruit_circuitpython_neopixel-6.3.9.dist-info/METADATA
adafruit_circuitpython_neopixel-6.3.9.dist-info/WHEEL
adafruit_circuitpython_neopixel-6.3.9.dist-info/top_level.txt
adafruit_circuitpython_neopixel-6.3.9.dist-info/RECORD
