Metadata-Version: 2.1
Name: adafruit-circuitpython-neopixel
Version: 6.3.9
Summary: CircuitPython library for NeoPixel LEDs.
Author-email: Adafruit Industries <circuitpython@adafruit.com>
License: MIT
Project-URL: Homepage, https://github.com/adafruit/Adafruit_CircuitPython_NeoPixel
Keywords: adafruit,neopixel,rgb,rgbw,led,hardware,micropython,circuitpython
Classifier: Intended Audience :: Developers
Classifier: Topic :: Software Development :: Libraries
Classifier: Topic :: Software Development :: Embedded Systems
Classifier: Topic :: System :: Hardware
Classifier: License :: OSI Approved :: MIT License
Classifier: Programming Language :: Python :: 3
License-File: LICENSE
Requires-Dist: Adafruit-Blinka
Requires-Dist: adafruit-circuitpython-pixelbuf
Provides-Extra: optional
